dj_kaos_utils/__init__.py
dj_kaos_utils/argparse.py
dj_kaos_utils/datetime.py
dj_kaos_utils/management.py
dj_kaos_utils/admin/__init__.py
dj_kaos_utils/admin/filters.py
dj_kaos_utils/admin/inlines.py
dj_kaos_utils/admin/mixins.py
dj_kaos_utils/admin/utils.py
dj_kaos_utils/forms/__init__.py
dj_kaos_utils/forms/fields.py
dj_kaos_utils/forms/forms.py
dj_kaos_utils/models/__init__.py
dj_kaos_utils/models/admin.py
dj_kaos_utils/models/fields.py
dj_kaos_utils/models/mixins.py
dj_kaos_utils/models/querysets.py
dj_kaos_utils/models/utils.py
dj_kaos_utils/rest/__init__.py
dj_kaos_utils/rest/serializers.py
dj_kaos_utils/rest/utils.py
dj_kaos_utils-0.1.0rc2.data/scripts/mg
dj_kaos_utils-0.1.0rc2.data/scripts/mkmg
tests/__init__.py
tests/test_argparse.py
tests/test_datetime.py
tests/test_forms.py
tests/test_management.py
tests/admin/__init__.py
tests/admin/test_filters.py
tests/admin/test_inlines.py
tests/admin/test_mixins.py
tests/admin/test_utils.py
tests/models/__init__.py
tests/models/test_fields.py
tests/models/test_mixins.py
tests/models/test_querysets.py
tests/rest/__init__.py
tests/rest/test_serializers.py
tests/rest/test_serializers_list.py
tests/rest/test_serializers_nested.py
dj_kaos_utils-0.1.0rc2.dist-info/LICENSE
dj_kaos_utils-0.1.0rc2.dist-info/METADATA
dj_kaos_utils-0.1.0rc2.dist-info/WHEEL
dj_kaos_utils-0.1.0rc2.dist-info/top_level.txt
dj_kaos_utils-0.1.0rc2.dist-info/RECORD
